{
  "replace": false,
  "order": 1,
  "enabled": true,
  "origins": [
    "apotheosis:blacksmith",
    "apotheosis:warsmith",
    "apotheosis:warsmitha",
    "apotheosis:warsmithaa",
    "apotheosis:warsmithaaa",
    "apotheosis:warsmithaab",
    "apotheosis:warsmithab",
    "apotheosis:warsmithaba",
    "apotheosis:warsmithabb",
    "apotheosis:warsmithb",
    "apotheosis:warsmithba",
    "apotheosis:warsmithbaa",
    "apotheosis:warsmithbab",
    "apotheosis:warsmithbb",
    "apotheosis:warsmithbba",
    "apotheosis:warsmithbbb"
  ],
  "allow_random": true,
  "exclude_random": [
  ],
  "allow_random_unchoosable": false
}